python_tuner/__init__.py
python_tuner/guitar_standard.py
python_tuner/note_frequencies.py
python_tuner/play_frequencies.py
python_tuner/tune.py
python_tuner/violin_standard.py
python_tuner-0.1.1.dist-info/licenses/LICENSE
python_tuner-0.1.1.dist-info/METADATA
python_tuner-0.1.1.dist-info/WHEEL
python_tuner-0.1.1.dist-info/top_level.txt
python_tuner-0.1.1.dist-info/RECORD
