Metadata-Version: 2.4
Name: python-tuner
Version: 0.1.1
Summary: A small library for tuning musical instruments.
Author-email: Brian Mai <brianmai216@gmail.com>
License: MIT
Requires-Python: >=3.7
License-File: LICENSE
Requires-Dist: numpy
Requires-Dist: sounddevice
Dynamic: license-file
